data_connectors/__init__.py
data_connectors/aggrid.py
data_connectors/bigquery.py
data_connectors/drive.py
data_connectors/gcs.py
data_connectors/google_calendar.py
data_connectors/gsheets.py
data_connectors/mssql.py
data_connectors/s3.py
data_connectors/slack.py
data_connectors/transform.py
data_connectors-0.20.29.dist-info/METADATA
data_connectors-0.20.29.dist-info/WHEEL
data_connectors-0.20.29.dist-info/RECORD
